emdash_cli/__init__.py
emdash_cli/client.py
emdash_cli/clipboard.py
emdash_cli/design.py
emdash_cli/diff_renderer.py
emdash_cli/keyboard.py
emdash_cli/main.py
emdash_cli/server_manager.py
emdash_cli/session_store.py
emdash_cli/sse_renderer.py
emdash_cli/commands/__init__.py
emdash_cli/commands/agent.py
emdash_cli/commands/analyze.py
emdash_cli/commands/auth.py
emdash_cli/commands/db.py
emdash_cli/commands/embed.py
emdash_cli/commands/index.py
emdash_cli/commands/plan.py
emdash_cli/commands/projectmd.py
emdash_cli/commands/registry.py
emdash_cli/commands/research.py
emdash_cli/commands/rules.py
emdash_cli/commands/search.py
emdash_cli/commands/server.py
emdash_cli/commands/skills.py
emdash_cli/commands/spec.py
emdash_cli/commands/tasks.py
emdash_cli/commands/team.py
emdash_cli/commands/agent/__init__.py
emdash_cli/commands/agent/cli.py
emdash_cli/commands/agent/constants.py
emdash_cli/commands/agent/file_utils.py
emdash_cli/commands/agent/help.py
emdash_cli/commands/agent/interactive.py
emdash_cli/commands/agent/menus.py
emdash_cli/commands/agent/models.json
emdash_cli/commands/agent/onboarding.py
emdash_cli/commands/agent/profiles.py
emdash_cli/commands/agent/session_restore.py
emdash_cli/commands/agent/sse_listener.py
emdash_cli/commands/agent/handlers/__init__.py
emdash_cli/commands/agent/handlers/agents.py
emdash_cli/commands/agent/handlers/auth.py
emdash_cli/commands/agent/handlers/doctor.py
emdash_cli/commands/agent/handlers/hooks.py
emdash_cli/commands/agent/handlers/index.py
emdash_cli/commands/agent/handlers/mcp.py
emdash_cli/commands/agent/handlers/misc.py
emdash_cli/commands/agent/handlers/models.py
emdash_cli/commands/agent/handlers/multiuser.py
emdash_cli/commands/agent/handlers/registry.py
emdash_cli/commands/agent/handlers/rules.py
emdash_cli/commands/agent/handlers/sessions.py
emdash_cli/commands/agent/handlers/setup.py
emdash_cli/commands/agent/handlers/skills.py
emdash_cli/commands/agent/handlers/stats.py
emdash_cli-0.1.107.dist-info/METADATA
emdash_cli-0.1.107.dist-info/WHEEL
emdash_cli-0.1.107.dist-info/entry_points.txt
emdash_cli-0.1.107.dist-info/RECORD
