Metadata-Version: 2.4
Name: emdash-cli
Version: 0.1.107
Summary: EmDash CLI - Command-line interface for code intelligence
Author: Em Dash Team
Requires-Python: >=3.10
Requires-Dist: aiohttp>=3.9.0
Requires-Dist: click>=8.1.7
Requires-Dist: emdash-core
Requires-Dist: httpx>=0.25.0
Requires-Dist: prompt-toolkit>=3.0.43
Requires-Dist: rich>=13.7.0
Provides-Extra: dev
Requires-Dist: pytest-cov>=4.1.0; extra == 'dev'
Requires-Dist: pytest>=7.4.3; extra == 'dev'
